pandana2/__init__.py
pandana2/decay_functions.py
pandana2/dijkstra.py
pandana2/network.py
pandana2/utils.py
pandana2-0.0.3.dist-info/licenses/LICENSE
pandana2-0.0.3.dist-info/METADATA
pandana2-0.0.3.dist-info/WHEEL
pandana2-0.0.3.dist-info/top_level.txt
pandana2-0.0.3.dist-info/RECORD
