Metadata-Version: 2.4
Name: pandana2
Version: 0.0.3
Summary: Weighted aggregations along the local street network
Author-email: Fletcher Foti <ffoti@mapcraft.io>
Project-URL: Homepage, https://github.com/mapcraftlabs/pandana2
Project-URL: Issues, https://github.com/mapcraftlabs/pandana2/issues
Classifier: Programming Language :: Python :: 3
Classifier: Operating System :: OS Independent
Requires-Python: >=3.09
License-File: LICENSE
Dynamic: license-file
